xinvert/__init__.py
xinvert/apps.py
xinvert/core.py
xinvert/finitediffs.py
xinvert/numbas.py
xinvert/utils.py
xinvert-0.1.7.dist-info/LICENSE
xinvert-0.1.7.dist-info/METADATA
xinvert-0.1.7.dist-info/WHEEL
xinvert-0.1.7.dist-info/top_level.txt
xinvert-0.1.7.dist-info/RECORD
