Metadata-Version: 2.1
Name: xinvert
Version: 0.1.7
Summary: Invert geofluid problems based on xarray, using SOR iteration
Home-page: https://github.com/miniufo/xinvert
Author: miniufo
Author-email: miniufo@163.com
License: MIT
Keywords: invert inversion atmosphere ocean SOR successive-overrelaxation-iteration
Classifier: Programming Language :: Python :: 3.6
Classifier: Programming Language :: Python :: 3.7
License-File: LICENSE
Requires-Dist: numpy
Requires-Dist: xarray
Requires-Dist: dask
Requires-Dist: numba
